automata/Automata.py
automata/__init__.py
automata/exception/AutomataRequirementMissingException.py
automata/exception/__init__.py
persuader_technology_automata-0.0.6.dist-info/LICENSE
persuader_technology_automata-0.0.6.dist-info/METADATA
persuader_technology_automata-0.0.6.dist-info/WHEEL
persuader_technology_automata-0.0.6.dist-info/top_level.txt
persuader_technology_automata-0.0.6.dist-info/RECORD
